data_packer/__init__.py
data_packer/constant.py
data_packer/err.py
data_packer/checker/__init__.py
data_packer/checker/_base.py
data_packer/checker/helper.py
data_packer/container/__init__.py
data_packer/container/_base.py
data_packer/container/dict_container.py
data_packer/converter/__init__.py
data_packer/converter/_base.py
data_packer/converter/helper.py
data_packer/field/__init__.py
data_packer/field/_base.py
data_packer/field/multi.py
data_packer/field/single.py
data_packer/util/__init__.py
data_packer/util/ip.py
data_packer-1.0.1.dist-info/DESCRIPTION.rst
data_packer-1.0.1.dist-info/METADATA
data_packer-1.0.1.dist-info/RECORD
data_packer-1.0.1.dist-info/WHEEL
data_packer-1.0.1.dist-info/metadata.json
data_packer-1.0.1.dist-info/top_level.txt
