Metadata-Version: 2.0
Name: data-packer
Version: 1.0.1
Summary: A python library for check and convert src data container then set it into dst data container.
Home-page: https://github.com/ideascf/data-packer
Author: chenfei
Author-email: ideascf@163.com
License: MIT
Platform: any
Classifier: Natural Language :: Chinese (Simplified)
Classifier: License :: OSI Approved :: MIT License
Classifier: Intended Audience :: Developers
Classifier: Programming Language :: Python
Classifier: Programming Language :: Python :: 2.6
Classifier: Programming Language :: Python :: 2.7
Classifier: Programming Language :: Python :: 3
Classifier: Programming Language :: Python :: 3.3
Classifier: Programming Language :: Python :: 3.4
Classifier: Programming Language :: Python :: 3.5
Classifier: Topic :: Software Development :: Libraries :: Python Modules
Classifier: Topic :: Software Development :: Libraries :: Application Frameworks
Provides-Extra: testing
Requires-Dist: pytest; extra == 'testing'
